multisite/__init__.py
multisite/apps.py
multisite/exceptions.py
multisite/forms.py
multisite/hacks.py
multisite/threadlocals.py
multisite/utils.py
multisite/__pycache__/__init__.cpython-310.pyc
multisite/__pycache__/__init__.cpython-311.pyc
multisite/__pycache__/__init__.cpython-312.pyc
multisite/__pycache__/__init__.cpython-39.pyc
multisite/__pycache__/apps.cpython-312.pyc
multisite/__pycache__/exceptions.cpython-312.pyc
multisite/__pycache__/forms.cpython-310.pyc
multisite/__pycache__/forms.cpython-311.pyc
multisite/__pycache__/forms.cpython-312.pyc
multisite/__pycache__/forms.cpython-39.pyc
multisite/__pycache__/hacks.cpython-310.pyc
multisite/__pycache__/hacks.cpython-311.pyc
multisite/__pycache__/hacks.cpython-312.pyc
multisite/__pycache__/hacks.cpython-39.pyc
multisite/__pycache__/test_settings.cpython-310-pytest-6.2.5.pyc
multisite/__pycache__/test_settings.cpython-311-pytest-8.1.1.pyc
multisite/__pycache__/test_settings.cpython-312-pytest-7.4.4.pyc
multisite/__pycache__/test_settings.cpython-312-pytest-8.1.1.pyc
multisite/__pycache__/test_settings.cpython-39-pytest-6.2.5.pyc
multisite/__pycache__/tests.cpython-310-pytest-6.2.5.pyc
multisite/__pycache__/tests.cpython-311-pytest-8.1.1.pyc
multisite/__pycache__/tests.cpython-312-pytest-7.4.4.pyc
multisite/__pycache__/tests.cpython-312-pytest-8.1.1.pyc
multisite/__pycache__/tests.cpython-39-pytest-6.2.5.pyc
multisite/__pycache__/threadlocals.cpython-310.pyc
multisite/__pycache__/threadlocals.cpython-311.pyc
multisite/__pycache__/threadlocals.cpython-312.pyc
multisite/__pycache__/threadlocals.cpython-39.pyc
multisite/__pycache__/utils.cpython-312.pyc
multisite/admin/__init__.py
multisite/admin/alias_admin.py
multisite/admin/multisite_changelist.py
multisite/admin/multisite_model_admin.py
multisite/admin/__pycache__/__init__.cpython-312.pyc
multisite/admin/__pycache__/alias_admin.cpython-312.pyc
multisite/admin/__pycache__/multisite_changelist.cpython-312.pyc
django_multisite2-2.1.2.dist-info/LICENSE
django_multisite2-2.1.2.dist-info/METADATA
django_multisite2-2.1.2.dist-info/WHEEL
django_multisite2-2.1.2.dist-info/top_level.txt
django_multisite2-2.1.2.dist-info/RECORD
